[{"id":1,"first_name":"Fredrick","last_name":"Bernaldo","email":"fbernaldo0@51.la","gender":"Male","avatar":"https://robohash.org/exquiaaccusamus.bmp?size=50x50&set=set1"},
{"id":2,"first_name":"Pat","last_name":"Imms","email":"pimms1@topsy.com","gender":"Male","avatar":"https://robohash.org/euminaccusamus.png?size=50x50&set=set1"},
{"id":3,"first_name":"Cheryl","last_name":"Stansby","email":"cstansby2@businessweek.com","gender":"Female","avatar":"https://robohash.org/autemnisimolestias.jpg?size=50x50&set=set1"},
{"id":4,"first_name":"Morrie","last_name":"Skarin","email":"mskarin3@amazon.de","gender":"Male","avatar":"https://robohash.org/praesentiumautemvoluptas.png?size=50x50&set=set1"},
{"id":5,"first_name":"Amelita","last_name":"Baughan","email":"abaughan4@samsung.com","gender":"Female","avatar":"https://robohash.org/quiexet.bmp?size=50x50&set=set1"},
{"id":6,"first_name":"Jaquenetta","last_name":"Kippin","email":"jkippin5@blinklist.com","gender":"Female","avatar":"https://robohash.org/eligendiexercitationemut.jpg?size=50x50&set=set1"},
{"id":7,"first_name":"Adriana","last_name":"Oxtiby","email":"aoxtiby6@bluehost.com","gender":"Female","avatar":"https://robohash.org/occaecatisolutavelit.png?size=50x50&set=set1"},
{"id":8,"first_name":"Ignazio","last_name":"Samsonsen","email":"isamsonsen7@sciencedirect.com","gender":"Male","avatar":"https://robohash.org/dictaquieius.jpg?size=50x50&set=set1"},
{"id":9,"first_name":"Jaclin","last_name":"Pigne","email":"jpigne8@quantcast.com","gender":"Female","avatar":"https://robohash.org/velitdoloremdolorum.png?size=50x50&set=set1"},
{"id":10,"first_name":"Wang","last_name":"Scherer","email":"wscherer9@narod.ru","gender":"Male","avatar":"https://robohash.org/autemadipisciaut.png?size=50x50&set=set1"}]